CHANGES.txt
DEPENDENCES.txt
README.txt
setup.py
src/ng/__init__.py
src/ng.app.remotefs.egg-info/PKG-INFO
src/ng.app.remotefs.egg-info/SOURCES.txt
src/ng.app.remotefs.egg-info/dependency_links.txt
src/ng.app.remotefs.egg-info/namespace_packages.txt
src/ng.app.remotefs.egg-info/not-zip-safe
src/ng.app.remotefs.egg-info/requires.txt
src/ng.app.remotefs.egg-info/top_level.txt
src/ng/app/__init__.py
src/ng/app/remotefs/__init__.py
src/ng/app/remotefs/configure.zcml
src/ng/app/remotefs/exceptions.py
src/ng/app/remotefs/interfaces.py
src/ng/app/remotefs/ng.app.remotefs.txt
src/ng/app/remotefs/remotefs.txt
src/ng/app/remotefs/remoteobject.py
src/ng/app/remotefs/browser/__init__.py
src/ng/app/remotefs/browser/configure.zcml
src/ng/app/remotefs/browser/edit.pt
src/ng/app/remotefs/browser/remoteobject.py
src/ng/app/remotefs/etc/remotefs-configure.zcml
src/ng/app/remotefs/remoteconnector/__init__.py
src/ng/app/remotefs/remoteconnector/configure.zcml
src/ng/app/remotefs/remoteconnector/interfaces.py
src/ng/app/remotefs/remoteconnector/remoteconnector.py
src/ng/app/remotefs/remoteconnector/remoteconnector.txt
src/ng/app/remotefs/remoteconnector/remoteconnectorhttp.py
src/ng/app/remotefs/remoteconnector/remoteconnectorsvn.py
src/ng/app/remotefs/remoteconnector/svntest.py
src/ng/app/remotefs/remoteconnector/svnwrapper.py
src/ng/app/remotefs/remoteconnector/browser/__init__.py
src/ng/app/remotefs/remoteconnector/browser/configure.zcml
src/ng/app/remotefs/remoteconnectorvocabulary/__init__.py
src/ng/app/remotefs/remoteconnectorvocabulary/configure.zcml
src/ng/app/remotefs/remoteconnectorvocabulary/remoteconnectorvocabulary.py
src/ng/app/remotefs/remotecontainer/__init__.py
src/ng/app/remotefs/remotecontainer/configure.zcml
src/ng/app/remotefs/remotecontainer/interfaces.py
src/ng/app/remotefs/remotecontainer/remotecontainer.py
src/ng/app/remotefs/remotecontainer/remotecontainer.txt
src/ng/app/remotefs/remotecontainer/browser/__init__.py
src/ng/app/remotefs/remotecontainer/browser/configure.zcml
src/ng/app/remotefs/remotefactory/__init__.py
src/ng/app/remotefs/remotefactory/interfaces.py
src/ng/app/remotefs/remotefactory/remoteobject.py
src/ng/app/remotefs/remotefile/__init__.py
src/ng/app/remotefs/remotefile/configure.zcml
src/ng/app/remotefs/remotefile/interfaces.py
